aws_eventbridge_rules_syncer/__init__.py
aws_eventbridge_rules_syncer/rule_engine.py
aws_eventbridge_rules_syncer/rule_syncer.py
src/__init__.py
src/rule_engine.py
src/rule_syncer.py
aws_eventbridge_rule_syncer-3.1.0.dist-info/LICENSE
aws_eventbridge_rule_syncer-3.1.0.dist-info/METADATA
aws_eventbridge_rule_syncer-3.1.0.dist-info/WHEEL
aws_eventbridge_rule_syncer-3.1.0.dist-info/top_level.txt
aws_eventbridge_rule_syncer-3.1.0.dist-info/zip-safe
aws_eventbridge_rule_syncer-3.1.0.dist-info/RECORD
