Metadata-Version: 2.1
Name: aws-eventbridge-rule-syncer
Version: 3.1.0
Summary: Provides rule syncer and rule evaluator for AWS Event Bridge
Home-page: https://github.com/ackotech/aws-eventbridge-rule-syncer
Author: Akash Agarwal
Author-email: agarwalakash45@gmail.com 
License: BSD
Keywords: aws,event-bridge,rules
Platform: UNKNOWN
Classifier: Intended Audience :: Developers
Classifier: Intended Audience :: End Users/Desktop
Classifier: Intended Audience :: System Administrators
Classifier: Intended Audience :: Information Technology
Classifier: Intended Audience :: Other Audience
Classifier: Natural Language :: English
Classifier: Operating System :: OS Independent
Classifier: Operating System :: POSIX :: Linux
Classifier: Operating System :: Microsoft :: Windows
Classifier: Operating System :: MacOS :: MacOS X
Classifier: Programming Language :: Python :: 3
Classifier: Programming Language :: Python :: 3.4
Classifier: Programming Language :: Python :: 3.5
Classifier: Programming Language :: Python :: 3.6
Classifier: Topic :: Software Development
Requires-Dist: boto3
